xfit/Constants.py
xfit/Continuum.py
xfit/FitMath.py
xfit/SimpleMath.py
xfit/SpectrumClass.py
xfit/__init__.py
xfit/version.py
xfit-0.1.1.0.dist-info/METADATA
xfit-0.1.1.0.dist-info/WHEEL
xfit-0.1.1.0.dist-info/top_level.txt
xfit-0.1.1.0.dist-info/RECORD
