Metadata-Version: 2.1
Name: xfit
Version: 0.1.1.0
Summary: Package for fitting XRF spectra. Based on xraylib
Home-page: https://github.com/linssab/xrffitting
Author: Sergio A. B. Lins
Author-email: sergio.lins@roma3.infn.it
License: MIT
Platform: UNKNOWN
Requires-Dist: numpy (>=1.18.1)
Requires-Dist: compwizard (>=0.1.2)
Requires-Dist: scipy (>=1.4.1)
